md2notion/NotionPyRenderer.py
md2notion/__init__.py
md2notion/__main__.py
md2notion/upload.py
md2notion-2.4.1.dist-info/LICENSE.txt
md2notion-2.4.1.dist-info/METADATA
md2notion-2.4.1.dist-info/WHEEL
md2notion-2.4.1.dist-info/top_level.txt
md2notion-2.4.1.dist-info/RECORD
